var pointsJson = {
  "type": "FeatureCollection",
  "name": "points",
  "features": [
    {
      "type": "Feature",
      "properties": {},
      "geometry": {
        "coordinates": [
          77.56054099999858,
          13.00071332305157
        ],
        "type": "Point",
      }
    },
    {
      "type": "Feature",
      "properties": {},
      "geometry": {
        "coordinates": [
          77.56384099460672,
          12.990128673631844
        ],
        "type": "Point"
      }
    },
    {
      "type": "Feature",
      "properties": {},
      "geometry": {
        "coordinates": [
          77.54281583290981,
          12.98107810337902
        ],
        "type": "Point"
      }
    },
    {
      "type": "Feature",
      "properties": {},
      "geometry": {
        "coordinates": [
          77.59682554705654,
          13.02376782266839
        ],
        "type": "Point"
      }
    }
  ]
}